pywell/entry_points.py
pywell/get_psql_results.py
pywell/notify_slack.py
pywell/secrets_manager.py
mo_pywell-1.1.0.dist-info/LICENSE
mo_pywell-1.1.0.dist-info/METADATA
mo_pywell-1.1.0.dist-info/WHEEL
mo_pywell-1.1.0.dist-info/top_level.txt
mo_pywell-1.1.0.dist-info/RECORD
