Metadata-Version: 2.1
Name: mo-pywell
Version: 1.1.0
Summary: A collection of independent Python scripts following the Unix philosphy of doing one thing well. Forked from https://github.com/sreynen/pywell.
Home-page: https://github.com/MoveOnOrg/pywell
Author: MoveOn, Scott Reynen
License: MIT
License-File: LICENSE
Requires-Dist: boto3
Requires-Dist: botocore
